QVAR/__init__.py
QVAR/qvar.py
QVAR/test.py
qvar-1.1.0.dist-info/METADATA
qvar-1.1.0.dist-info/WHEEL
qvar-1.1.0.dist-info/top_level.txt
qvar-1.1.0.dist-info/RECORD
