Metadata-Version: 2.4
Name: QVAR
Version: 1.1.0
Author: Alessandro Poggiali
Dynamic: author
Dynamic: description
Dynamic: description-content-type
